Metadata-Version: 2.1
Name: fastx
Version: 0.0.3
Summary: Just a simple kseq.h binding
Home-page: https://github.com/cjw85/fastx
Author: cwright
Author-email: chris.wright@oxfordnanopore.tech
License: UNKNOWN
Platform: UNKNOWN
Requires-Python: >=3.5.*,
